espy_pay/__init__.py
espy_pay/general/CONSTANTS.py
espy_pay/general/__init__.py
espy_pay/general/db.py
espy_pay/general/enums.py
espy_pay/general/model.py
espy_pay/general/pg.py
espy_pay/general/schema.py
espy_pay/general/util.py
espy_pay/ng/__init__.py
espy_pay/ng/paystack/__init__.py
espy_pay/ng/paystack/schema.py
espy_pay/ng/paystack/service.py
espy_pay/ng/paystack/util/Bankcodes.py
espy_pay/ng/paystack/util/CONSTANTS.py
espy_pay/ng/paystack/util/__init__.py
espy_pay/us/__init__.py
espy_pay/us/stripe/CONSTANTS.py
espy_pay/us/stripe/__init__.py
espy_pay/us/stripe/schema.py
espy_pay/us/stripe/service.py
tests/__init__.py
tests/config.py
tests/test_copyright.py
tests/validator.py
espy_pay-1.0.29.dist-info/LICENSE
espy_pay-1.0.29.dist-info/METADATA
espy_pay-1.0.29.dist-info/WHEEL
espy_pay-1.0.29.dist-info/top_level.txt
espy_pay-1.0.29.dist-info/RECORD
