Metadata-Version: 2.1
Name: espy-pay
Version: 1.0.29
Summary: Payment services aggregator for ESSL
Home-page: UNKNOWN
Author: Femi Adigun
Author-email: femi.adigun@myeverlasting.net
License: MIT
Keywords: payment, essl, aggregator, paystack, stripe, interswitch, square, flutterwave, payant
Platform: UNKNOWN
Classifier: Development Status :: 3 - Alpha
Classifier: Intended Audience :: Developers
Classifier: License :: OSI Approved :: MIT License
Classifier: Programming Language :: Python :: 3.9
License-File: LICENSE
Requires-Dist: bcrypt >=4.2.1
Requires-Dist: pytest >=8.3.4
Requires-Dist: pydantic >=2.10.6
Requires-Dist: sqlalchemy >=2.0.37
Requires-Dist: PyYAML >=6.0.2
Requires-Dist: httpx >=0.28.1
Requires-Dist: python-dotenv >=1.0.1
Requires-Dist: stripe >=11.5.0
